paperplot/__init__.py
paperplot/_contour_base.py
paperplot/_data_filter_base.py
paperplot/_figure_base.py
paperplot/contour_fig.py
paperplot/contour_grid_filter.py
paperplot/contour_line_fig.py
paperplot/contour_points_filter.py
paperplot/line_fig.py
paperplot/line_style.py
paperplot/mesh_fig.py
paperplot/pixel_contour_fig.py
paperplot/pixel_grid_filter.py
paperplot-0.4.6.dist-info/LICENSE
paperplot-0.4.6.dist-info/METADATA
paperplot-0.4.6.dist-info/WHEEL
paperplot-0.4.6.dist-info/top_level.txt
paperplot-0.4.6.dist-info/RECORD
